usereditor/__init__.py
usereditor/rest.py
usereditor/templates/usereditor/user_item.html
django_usereditor-0.0.8.dist-info/LICENSE.rst
django_usereditor-0.0.8.dist-info/METADATA
django_usereditor-0.0.8.dist-info/WHEEL
django_usereditor-0.0.8.dist-info/top_level.txt
django_usereditor-0.0.8.dist-info/RECORD
