Metadata-Version: 2.1
Name: django-usereditor
Version: 0.0.8
Summary: Aplication for user overview and editing
Home-page: https://github.com/Brontes/django-usereditor
Author: Klemen Pukl
Author-email: klemen.pukl@velis.si
License: BSD-3-Clause
Classifier: Development Status :: 3 - Alpha
Classifier: Programming Language :: Python :: 3
Classifier: License :: OSI Approved :: BSD License
Classifier: Operating System :: OS Independent
Classifier: Framework :: Django
Requires-Python: >=3.4
License-File: LICENSE.rst
Requires-Dist: six
Requires-Dist: pytz
Requires-Dist: coreapi (>=1.32)
Requires-Dist: django (>=1.10)
Requires-Dist: djangorestframework (>=3.4)
Requires-Dist: dynamicforms (>=0.70.0)
Requires-Dist: typing ; python_version < "3.5"
